{"279266228151779329":[{"name":"Boykisser","image":"https://cdn.discordapp.com/emojis/1192198905698463874.webp"}],"943587026576486410":[{"name":"Yep","image":"https://cdn.discordapp.com/emojis/858660472755716097.gif"}],"889528189079134209":[{"name":"PetPet","image":"https://cdn.discordapp.com/emojis/1196175290930573332.gif"}],"1140367031963754607":[{"name":"Попатряс","image":"https://cdn.discordapp.com/emojis/1130869643783975014.gif"}],"409834601180037131":[{"name":"Батя булки","image":"https://cdn.discordapp.com/emojis/448473502874337281.webp"}]}
